{
    "education": [
        {
            "grade": "Universidad",
            "date": "2017-Actualmente",
            "name": "Ingenieria en Sistemas Computacionales."
        },
        {
            "grade": "Preparatoria",
            "date": "2013-2016",
            "name": "Tecnico en Programacion."
        }
    ],
    "experience": [
        {
            "date": "Oct 2021-Enero 2022",
            "description": "Residencias",
            "place": "Codeway soluciones Integrales"
        }
    ],
    "skills":[
        {
            "frontend":[
                {
                    "name": "HTML",
                    "icon": "fa-brands fa-html5",
                    "color":""
                },
                {
                    "name": "CSS",
                    "icon": "fa-brands fa-css3-alt",
                    "color":""
                },
                {
                    "name": "JavaScript",
                    "icon": "fa-brands fa-js-square",
                    "color":""
                },
                {
                    "name": "React",
                    "icon": "fa-brands fa-react",
                    "color":""
                },
                {
                    "name": "Bootstrap",
                    "icon": "fa-brands fa-bootstrap",
                    "color":""
                }
            ],
            "backend":[
                {
                    "name": "PHP",
                    "icon": "fa-brands fa-php",
                    "color":""
                },
                {
                    "name": "Nodejs",
                    "icon": "fa-brands fa-node",
                    "color":""
                }
            ],
            "database":[
                {
                    "name": "MySQL",
                    "ruta": "./img/mysql.svg",
                    "color":""
                },
                {
                    "name": "MongoDB",
                    "ruta": "https://img.icons8.com/external-tal-revivo-light-tal-revivo/24/000000/external-mongodb-a-cross-platform-document-oriented-database-program-logo-light-tal-revivo.png",
                    "color":""
                }
            ]
        }
    ]
}